pibooth_nextcloud.py
pibooth_nextcloud-1.0.7.dist-info/LICENSE
pibooth_nextcloud-1.0.7.dist-info/METADATA
pibooth_nextcloud-1.0.7.dist-info/WHEEL
pibooth_nextcloud-1.0.7.dist-info/entry_points.txt
pibooth_nextcloud-1.0.7.dist-info/top_level.txt
pibooth_nextcloud-1.0.7.dist-info/RECORD
