Metadata-Version: 2.1
Name: pibooth-nextcloud
Version: 1.0.7
Summary: Pibooth plugin to upload photos to Nextcloud
Home-page: https://github.com/ceeeeb/pibooth-nextcloud
Download-URL: https://github.com/ceeeeb/pibooth-nextcloud/archive/1.0.7.tar.gz
Author: Ceeeeb
License: MIT license
Keywords: Raspberry Pi,camera,photobooth,nextcloud
Platform: unix
Platform: linux
Classifier: Development Status :: 5 - Production/Stable
Classifier: Environment :: Other Environment
Classifier: Intended Audience :: Developers
Classifier: Intended Audience :: End Users/Desktop
Classifier: License :: OSI Approved :: MIT License
Classifier: Operating System :: POSIX :: Linux
Classifier: Programming Language :: Python :: 3.4
Classifier: Programming Language :: Python :: 3.6
Classifier: Natural Language :: English
Classifier: Topic :: Multimedia :: Graphics :: Capture :: Digital Camera
License-File: LICENSE
Requires-Dist: pibooth >=2.0.0
Requires-Dist: pyocclient ==0.4
Requires-Dist: qrcode >=6.1
